allbluepy/License.txt
allbluepy/README.md
allbluepy/__allblue__.py
allbluepy/__init__.py
allbluepy/ecorregião.csv
allbluepy/província.csv
allbluepy/região.csv
allbluepy/zona_economica.csv
allbluepy-0.2.0.dist-info/METADATA
allbluepy-0.2.0.dist-info/WHEEL
allbluepy-0.2.0.dist-info/top_level.txt
allbluepy-0.2.0.dist-info/RECORD
