Metadata-Version: 2.1
Name: allbluepy
Version: 0.2.0
Summary: Informações oceânicas referente a região mais próxima as cordenadas de entrada
Home-page: https://github.com/BSFernando
Author: Fernando Borges
Author-email: bs_fernando@hotmail.com
License: MIT License
Keywords: packages
Platform: UNKNOWN
Requires-Dist: pandas
